chaoskafka/__init__.py
chaoskafka/actions.py
chaoskafka/controls/__init__.py
chaoskafka/controls/get_production_offsets.py
chaoskafka/probes.py
chaoskafka/utils.py
chaostoolkit_kafka-0.1.2.dist-info/METADATA
chaostoolkit_kafka-0.1.2.dist-info/WHEEL
chaostoolkit_kafka-0.1.2.dist-info/licenses/LICENSE
chaostoolkit_kafka-0.1.2.dist-info/RECORD
