Metadata-Version: 2.1
Name: chaostoolkit-kafka
Version: 0.1.2
Summary: Kafka extension for Chaos Toolkit extensions
Author-Email: Jorge Tapicha <jitapichab@gmail.com>
License: Apache-2.0
Classifier: Development Status :: 5 - Production/Stable
Classifier: Intended Audience :: Developers
Classifier: License :: Freely Distributable
Classifier: License :: OSI Approved :: Apache Software License
Classifier: Operating System :: OS Independent
Classifier: Programming Language :: Python
Classifier: Programming Language :: Python :: 3
Classifier: Programming Language :: Python :: 3.8
Classifier: Programming Language :: Python :: 3.9
Classifier: Programming Language :: Python :: 3.10
Classifier: Programming Language :: Python :: 3.11
Classifier: Programming Language :: Python :: 3.12
Classifier: Programming Language :: Python :: Implementation
Classifier: Programming Language :: Python :: Implementation :: CPython
Project-URL: Repository, https://github.com/jitapichab/chaostoolkit-kafka
Project-URL: Changelog, https://github.com/jitapichab/chaostoolkit-kafka/blob/master/README.md
Requires-Python: >=3.8
Requires-Dist: chaostoolkit-lib>=1.42.0
Requires-Dist: confluent-kafka>=2.3.0
